django_geoaxis/__init__.py
django_geoaxis/backends/__init__.py
django_geoaxis/backends/geoaxis.py
django_geoaxis-0.0.2.dist-info/LICENSE
django_geoaxis-0.0.2.dist-info/METADATA
django_geoaxis-0.0.2.dist-info/WHEEL
django_geoaxis-0.0.2.dist-info/top_level.txt
django_geoaxis-0.0.2.dist-info/RECORD
