Metadata-Version: 2.1
Name: django-geoaxis
Version: 0.0.2
Summary: A Django authentication backend for GeoAxIS
Home-page: https://gitlab.devops.geointservices.io/boundlessgeo/django-geoaxis
Author: Boundless Spatial
Author-email: contact@boundlessgeo.com
License: UNKNOWN
Download-URL: https://gitlab.devops.geointservices.io/boundlessgeo/django-geoaxis
Platform: UNKNOWN
Classifier: Topic :: Utilities
Classifier: Intended Audience :: System Administrators
Classifier: Environment :: Web Environment
Classifier: License :: OSI Approved :: MIT License
Classifier: Development Status :: 3 - Alpha
Classifier: Operating System :: Other OS
Classifier: Programming Language :: Python :: 2.7
Requires-Dist: certifi
Requires-Dist: httplib2
Requires-Dist: requests
Requires-Dist: social-auth-core
